bing_chat/BingGPT.py
bing_chat/BingUtils.py
bing_chat/ImageGen.py
bing_chat/__init__.py
bing_chat/chathub.py
bing_chat/constants.py
bing_chat/conversation.py
bing_chat/conversation_style.py
bing_chat/exceptions.py
bing_chat/locale.py
bing_chat/main.py
bing_chat/request.py
bing_chat/utilities.py
bing_chat-1.9.5.dist-info/LICENSE
bing_chat-1.9.5.dist-info/METADATA
bing_chat-1.9.5.dist-info/WHEEL
bing_chat-1.9.5.dist-info/entry_points.txt
bing_chat-1.9.5.dist-info/RECORD
